games/__init__.py
games/hangman.py
games/rock_paper_scissors.py
games/words.py
Dual_double_games-0.1.0.dist-info/METADATA
Dual_double_games-0.1.0.dist-info/WHEEL
Dual_double_games-0.1.0.dist-info/top_level.txt
Dual_double_games-0.1.0.dist-info/RECORD
