Metadata-Version: 2.1
Name: Dual-double-games
Version: 0.1.0
Summary: A package containing two games, hangman, rock_paper_scissors.
Home-page: UNKNOWN
Author: Matt
Author-email: matthew.alsop@dci-student.org
License: UNKNOWN
Platform: UNKNOWN
Classifier: Programming Language :: Python :: 3
Classifier: License :: OSI Approved :: MIT License
Classifier: Operating System :: OS Independent
Requires-Python: >=3.6
Requires-Dist: colorama
Requires-Dist: datetime
Requires-Dist: timedelta
